demo.py
setup.cfg
setup.py
pybitx/__init__.py
pybitx/api.py
pybitx/meta.py
pybitx.egg-info/PKG-INFO
pybitx.egg-info/SOURCES.txt
pybitx.egg-info/dependency_links.txt
pybitx.egg-info/requires.txt
pybitx.egg-info/top_level.txt