Metadata-Version: 1.1
Name: pybitx
Version: 0.1.11
Summary: A BitX API for Python
Home-page: https://github.com/CjS77/pybitx
Author: Cayle Sharrock
Author-email: cayle@nimbustech.biz
License: MIT
Download-URL: https://github.com/CjS77/pybitx/tarball/0.1.11
Keywords: BitX Bitcoin exchange API
Platform: UNKNOWN
